stackit/iaasalpha/__init__.py
stackit/iaasalpha/api/__init__.py
stackit/iaasalpha/api/default_api.py
stackit/iaasalpha/api_client.py
stackit/iaasalpha/api_response.py
stackit/iaasalpha/configuration.py
stackit/iaasalpha/exceptions.py
stackit/iaasalpha/models/__init__.py
stackit/iaasalpha/models/add_member_to_virtual_ip_payload.py
stackit/iaasalpha/models/add_volume_to_server_payload.py
stackit/iaasalpha/models/allowed_addresses_inner.py
stackit/iaasalpha/models/area.py
stackit/iaasalpha/models/area_config.py
stackit/iaasalpha/models/area_id.py
stackit/iaasalpha/models/area_prefix_config_ipv4.py
stackit/iaasalpha/models/base_security_group_rule.py
stackit/iaasalpha/models/boot_volume.py
stackit/iaasalpha/models/boot_volume_source.py
stackit/iaasalpha/models/create_area_address_family.py
stackit/iaasalpha/models/create_area_ipv4.py
stackit/iaasalpha/models/create_image_payload.py
stackit/iaasalpha/models/create_key_pair_payload.py
stackit/iaasalpha/models/create_nic_payload.py
stackit/iaasalpha/models/create_protocol.py
stackit/iaasalpha/models/create_public_ip_payload.py
stackit/iaasalpha/models/create_security_group_payload.py
stackit/iaasalpha/models/create_security_group_rule_payload.py
stackit/iaasalpha/models/create_security_group_rule_protocol.py
stackit/iaasalpha/models/create_server_networking.py
stackit/iaasalpha/models/create_server_networking_with_nics.py
stackit/iaasalpha/models/create_server_payload.py
stackit/iaasalpha/models/create_server_payload_networking.py
stackit/iaasalpha/models/create_virtual_ip_payload.py
stackit/iaasalpha/models/create_volume_payload.py
stackit/iaasalpha/models/error.py
stackit/iaasalpha/models/get_server_log200_response.py
stackit/iaasalpha/models/get_server_log_request.py
stackit/iaasalpha/models/icmp_parameters.py
stackit/iaasalpha/models/image.py
stackit/iaasalpha/models/image_config.py
stackit/iaasalpha/models/image_create_response.py
stackit/iaasalpha/models/image_list_response.py
stackit_iaasalpha-0.0.1a0.dist-info/METADATA
stackit_iaasalpha-0.0.1a0.dist-info/WHEEL
stackit_iaasalpha-0.0.1a0.dist-info/RECORD
