Metadata-Version: 2.1
Name: stackit-iaasalpha
Version: 0.0.1a0
Summary: IaaS-API
Author: STACKIT Developer Tools
Author-email: developer-tools@stackit.cloud
Requires-Python: >=3.8,<4.0
Classifier: License :: OSI Approved :: Apache Software License
Classifier: Operating System :: OS Independent
Classifier: Programming Language :: Python :: 3
Classifier: Programming Language :: Python :: 3.8
Classifier: Programming Language :: Python :: 3.9
Classifier: Programming Language :: Python :: 3.10
Classifier: Programming Language :: Python :: 3.11
Classifier: Programming Language :: Python :: 3.12
Classifier: Programming Language :: Python :: 3.13
Requires-Dist: pydantic (>=2.9.2)
Requires-Dist: python-dateutil (>=2.9.0.post0)
Requires-Dist: requests (>=2.32.3)
Requires-Dist: stackit-core (>=0.0.1a)
